[
    {
      "name": "Bitwarden",
      "url": "https://bitwarden.com/",
      "description": "Open-source password manager with secure vault."
    },
    {
      "name": "KeePass",
      "url": "https://keepass.info/",
      "description": "Free offline password manager."
    },
    {
      "name": "LastPass",
      "url": "https://www.lastpass.com/",
      "description": "Cloud-based password manager for personal use."
    },
    {
      "name": "NordPass",
      "url": "https://nordpass.com/",
      "description": "Secure password storage and autofill tool."
    }
  ]
  